trakt_scrobbler/__init__.py
trakt_scrobbler/__main__.py
trakt_scrobbler/__version__.py
trakt_scrobbler/app_dirs.py
trakt_scrobbler/backlog_cleaner.py
trakt_scrobbler/commands/__init__.py
trakt_scrobbler/commands/autostart.py
trakt_scrobbler/commands/backlog.py
trakt_scrobbler/commands/command.py
trakt_scrobbler/commands/config.py
trakt_scrobbler/commands/init.py
trakt_scrobbler/commands/log.py
trakt_scrobbler/commands/lookup.py
trakt_scrobbler/commands/plex.py
trakt_scrobbler/commands/remap.py
trakt_scrobbler/commands/run.py
trakt_scrobbler/commands/start.py
trakt_scrobbler/commands/status.py
trakt_scrobbler/commands/stop.py
trakt_scrobbler/commands/test.py
trakt_scrobbler/commands/trakt.py
trakt_scrobbler/commands/whitelist.py
trakt_scrobbler/config_default.yaml
trakt_scrobbler/console.py
trakt_scrobbler/file_info.py
trakt_scrobbler/log_config.py
trakt_scrobbler/main.py
trakt_scrobbler/mediainfo_remap.py
trakt_scrobbler/notifier.py
trakt_scrobbler/player_monitors/__init__.py
trakt_scrobbler/player_monitors/monitor.py
trakt_scrobbler/player_monitors/mpc.py
trakt_scrobbler/player_monitors/mpv.py
trakt_scrobbler/player_monitors/mpv_wrappers.py
trakt_scrobbler/player_monitors/plex.py
trakt_scrobbler/player_monitors/vlc.py
trakt_scrobbler/scrobbler.py
trakt_scrobbler/trakt_auth.py
trakt_scrobbler/trakt_interface.py
trakt_scrobbler/trakt_key_holder.py
trakt_scrobbler/utils.py
trakt_scrobbler-1.8.0.dist-info/METADATA
trakt_scrobbler-1.8.0.dist-info/WHEEL
trakt_scrobbler-1.8.0.dist-info/entry_points.txt
trakt_scrobbler-1.8.0.dist-info/licenses/LICENSE
trakt_scrobbler-1.8.0.dist-info/RECORD
