Metadata-Version: 2.4
Name: trakt-scrobbler
Version: 1.8.0
Summary: Scrobbler for trakt.tv that supports VLC, Plex, MPC-HC, and MPV
License: GPL-2.0-only
License-File: LICENSE
Keywords: trakt,scrobbler
Author: iamkroot
Author-email: kroot.patel@gmail.com
Requires-Python: >=3.9,<3.15
Classifier: Development Status :: 5 - Production/Stable
Classifier: Intended Audience :: End Users/Desktop
Classifier: License :: OSI Approved :: GNU General Public License v2 (GPLv2)
Classifier: Operating System :: OS Independent
Classifier: Programming Language :: Python :: 3
Classifier: Programming Language :: Python :: 3.9
Classifier: Programming Language :: Python :: 3.10
Classifier: Programming Language :: Python :: 3.11
Classifier: Programming Language :: Python :: 3.12
Classifier: Programming Language :: Python :: 3.13
Classifier: Programming Language :: Python :: 3.14
Provides-Extra: socks
Requires-Dist: appdirs (>=1.4.4,<2.0.0)
Requires-Dist: cleo (>=0.8.1,<0.9.0)
Requires-Dist: confuse (>=2.0,<3.0)
Requires-Dist: desktop-notifier (>=6.1.0,<7.0.0)
Requires-Dist: guessit (>=3.7.1,<4.0.0)
Requires-Dist: pydantic (>=2.4,<3.0)
Requires-Dist: pydantic-core (>=2.10.1,<3.0.0)
Requires-Dist: pysocks (>=1.7.1,<2.0.0) ; extra == "socks"
Requires-Dist: pywin32 (>=227) ; sys_platform == "win32"
Requires-Dist: requests (>=2.31.0,<3.0.0)
Requires-Dist: tomli (>=2.0.1,<3.0.0) ; python_version < "3.11"
Requires-Dist: urllib3 (>=2.5.0,<3.0.0)
Requires-Dist: urlmatch (>=1.0.1,<2.0.0)
Project-URL: Repository, https://github.com/iamkroot/trakt-scrobbler
